Workbook

Sheet Products
A3: Toasters101
A6: Products
A8: Product_ID | B8: Product Name | C8: Category | D8: Price | E8: Cost
A9: P001 | B9: Espresso Small | C9: Hot Drink | D9: 22 | E9: 12
A10: P002 | B10: Espresso Regular | C10: Hot Drink | D10: 26 | E10: 14
A11: P003 | B11: Espresso Large | C11: Hot Drink | D11: 30 | E11: 16
A12: P004 | B12: Americano Small | C12: Hot Drink | D12: 25 | E12: 14
A13: P005 | B13: Americano Regular | C13: Hot Drink | D13: 30 | E13: 17
A14: P006 | B14: Americano Large | C14: Hot Drink | D14: 34 | E14: 19
A15: P007 | B15: Cappuccino Small | C15: Hot Drink | D15: 28 | E15: 16
A16: P008 | B16: Cappuccino Regular | C16: Hot Drink | D16: 32 | E16: 18
A17: P009 | B17: Cappuccino Large | C17: Hot Drink | D17: 36 | E17: 21
A18: P010 | B18: Latte Small | C18: Hot Drink | D18: 30 | E18: 17
A19: P011 | B19: Latte Regular | C19: Hot Drink | D19: 34 | E19: 19
A20: P012 | B20: Latte Large | C20: Hot Drink | D20: 38 | E20: 22
... A94: P086 | B94: Toasties101 Cap | C94: Retail | D94: 120 | E94: 80

Sheet Inventory
A3: Toasters101
A6: Inventory
A8: Product_ID | B8: Starting_Stock | C8: Quantity_Sold | D8: Remaining_Stock | E8: Low_Stock_Flag
A9: P001 | B9: 24 | C9: =IFERROR(SUMIF(Sales!C:C, A9, Sales!E:E), 0) -> 0 | D9: =IFERROR(B10 - C10, 0) -> 23 | E9: =IF(D9<5, "Low", "Ok") -> Ok
A10: P002 | B10: 23 | C10: =IFERROR(SUMIF(Sales!C:C, A10, Sales!E:E), 0) -> 0 | D10: =IFERROR(B11 - C11, 0) -> 46 | E10: =IF(D10<5, "Low", "Ok") -> Ok
A11: P003 | B11: 46 | C11: =IFERROR(SUMIF(Sales!C:C, A11, Sales!E:E), 0) -> 0 | D11: =IFERROR(B12 - C12, 0) -> 21 | E11: =IF(D11<5, "Low", "Ok") -> Ok
A12: P004 | B12: 21 | C12: =IFERROR(SUMIF(Sales!C:C, A12, Sales!E:E), 0) -> 0 | D12: =IFERROR(B13 - C13, 0) -> 4 | E12: =IF(D12<5, "Low", "Ok") -> Low
A13: P005 | B13: 4 | C13: =IFERROR(SUMIF(Sales!C:C, A13, Sales!E:E), 0) -> 0 | D13: =IFERROR(B14 - C14, 0) -> 33 | E13: =IF(D13<5, "Low", "Ok") -> Ok
A14: P006 | B14: 33 | C14: =IFERROR(SUMIF(Sales!C:C, A14, Sales!E:E), 0) -> 0 | D14: =IFERROR(B15 - C15, 0) -> 8 | E14: =IF(D14<5, "Low", "Ok") -> Ok
A15: P007 | B15: 8 | C15: =IFERROR(SUMIF(Sales!C:C, A15, Sales!E:E), 0) -> 0 | D15: =IFERROR(B16 - C16, 0) -> 5 | E15: =IF(D15<5, "Low", "Ok") -> Ok
A16: P008 | B16: 5 | C16: =IFERROR(SUMIF(Sales!C:C, A16, Sales!E:E), 0) -> 0 | D16: =IFERROR(B17 - C17, 0) -> 22 | E16: =IF(D16<5, "Low", "Ok") -> Ok
A17: P009 | B17: 22 | C17: =IFERROR(SUMIF(Sales!C:C, A17, Sales!E:E), 0) -> 0 | D17: =IFERROR(B18 - C18, 0) -> 35 | E17: =IF(D17<5, "Low", "Ok") -> Ok
A18: P010 | B18: 35 | C18: =IFERROR(SUMIF(Sales!C:C, A18, Sales!E:E), 0) -> 0 | D18: =IFERROR(B19 - C19, 0) -> 6 | E18: =IF(D18<5, "Low", "Ok") -> Ok
A19: P011 | B19: 6 | C19: =IFERROR(SUMIF(Sales!C:C, A19, Sales!E:E), 0) -> 0 | D19: =IFERROR(B20 - C20, 0) -> 3 | E19: =IF(D19<5, "Low", "Ok") -> Low
A20: P012 | B20: 4 | C20: =IFERROR(SUMIF(Sales!C:C, A20, Sales!E:E), 0) -> 1 | D20: =IFERROR(B21 - C21, 0) -> 23 | E20: =IF(D20<5, "Low", "Ok") -> Ok
... A94: P086 | B94: 29 | C94: =IFERROR(SUMIF(Sales!C:C, A94, Sales!E:E), 0) -> 0 | D94: =IFERROR(B95 - C95, 0) -> 0 | E94: =IF(D94<5, "Low", "Ok") -> Low

Sheet Sales
A3: Toasters101
A6: Sales
A8: Date | B8: Sale_ID | C8: Product_ID | D8: Price | E8: Quantity | F8: Payment_Type | G8: Amount
A9: 46069 | B9: S001 | C9: P060 | D9: =IFERROR(VLOOKUP(C9, Products!A:D, 4, FALSE), "") -> 65 | E9: 3 | F9: Tab | G9: =D9*E9 -> 195
A10: 46069 | B10: S002 | C10: P071 | D10: =IFERROR(VLOOKUP(C10, Products!A:D, 4, FALSE), "") -> 6 | E10: 1 | F10: Card | G10: =D10*E10 -> 6
A11: 46069 | B11: S002 | C11: P063 | D11: =IFERROR(VLOOKUP(C11, Products!A:D, 4, FALSE), "") -> 22 | E11: 1 | F11: Cash | G11: =D11*E11 -> 22
A12: 46069 | B12: S003 | C12: P064 | D12: =IFERROR(VLOOKUP(C12, Products!A:D, 4, FALSE), "") -> 22 | E12: 2 | F12: Cash | G12: =D12*E12 -> 44
A13: 46069 | B13: S004 | C13: P012 | D13: =IFERROR(VLOOKUP(C13, Products!A:D, 4, FALSE), "") -> 38 | E13: 1 | F13: Tab | G13: =D13*E13 -> 38
A14: 46069 | B14: S005 | C14: P016 | D14: =IFERROR(VLOOKUP(C14, Products!A:D, 4, FALSE), "") -> 32 | E14: 1 | F14: Tab | G14: =D14*E14 -> 32
A15: 46069 | B15: S006 | C15: P025 | D15: =IFERROR(VLOOKUP(C15, Products!A:D, 4, FALSE), "") -> 22 | E15: 1 | F15: Tab | G15: =D15*E15 -> 22

Sheet Customer_Tabs
A3: Toasters101
A6: Customer Tabs
A8: Customer_Name | B8: Sales_ID | C8: Total | D8: Status
A9: Diogo Dalot | B9: S001 | C9: =IFERROR(SUMIFS(Sales!G:G, Sales!F:F, "Tab", Sales!B:B, B9), 0) -> 195 | D9: Outstanding
A10: Mfundo Vilakazi | B10: S004 | C10: =IFERROR(SUMIFS(Sales!G:G, Sales!F:F, "Tab", Sales!B:B, B10), 0) -> 38 | D10: Paid
A11: Tshepo Masilela | B11: S005 | C11: =IFERROR(SUMIFS(Sales!G:G, Sales!F:F, "Tab", Sales!B:B, B11), 0) -> 32 | D11: Paid
A12: Tyrell Malacia | B12: S006 | C12: =IFERROR(SUMIFS(Sales!G:G, Sales!F:F, "Tab", Sales!B:B, B12), 0) -> 22 | D12: Outstanding
